rmi2mid.py
rmi2mid-0.1.dist-info/LICENSE
rmi2mid-0.1.dist-info/METADATA
rmi2mid-0.1.dist-info/WHEEL
rmi2mid-0.1.dist-info/top_level.txt
rmi2mid-0.1.dist-info/RECORD
