Metadata-Version: 2.1
Name: rmi2mid
Version: 0.1
Summary: Extract Standard MIDI file (.mid) from RIFF MIDI (RMID) file (.rmi or .mid).
Home-page: https://github.com/alextwl/rmi2mid
Author: Wei-Li Tang
Author-email: alex@ip6.tw
License: UNKNOWN
Platform: UNKNOWN
Classifier: Programming Language :: Python :: 3
Classifier: License :: OSI Approved :: MIT License
Classifier: Operating System :: OS Independent
Classifier: Topic :: Multimedia :: Sound/Audio :: Conversion
Classifier: Topic :: Multimedia :: Sound/Audio :: MIDI
